{"url":"http://www.obchod-boty.cz/index.php?kat_cislo=851709300000-en-%3Estudentsky-batoh-topgal-hit-812-g&rezim=osetrovani&sekce=detail_polozky","image":"obchod-boty-000215","typedObjects":[{"boundingBox":[941,200,1434,292],"text":"Studentský batoh TOPGAL HIT 812-G","type":"name"},{"boundingBox":[1190,524,1432,574],"text":"1 299 Kč","type":"price"},{"boundingBox":[491,273,931,713],"text":"","type":"main_image"},{"boundingBox":[942,773,1434,935],"text":"  Vážení zákazníci,    děkujeme Vám, že jste si zakoupili zboží v našem e-shopu a doufáme, že Vám bude dlouho sloužit a budete s ním spokojeni.    Naším cílem je Vaše spokojenost, a proto si dovolujeme Vám poskytnout několik doporučení jak se zakoupenou obuví zacházet:     Při výběru obuvi pečlivě zvažte účel, k němuž bude obuv používána:       Společenská obuv - je určena pro nošení v interiéru. Nehodí se k delší chůzi, je velmi citlivá na mokro a nerovný povrch.     Vycházková obuv - je určena na běžné nošení.    Rekreační obuv - je určena pro volný čas, rekreační sport.    Sportovní obuv - je určena vždy pro konkrétní skupinu sportů.   Domácí obuv - je určena jako přezůvková obuv v domácnosti.      Výskyt vady, která vznikla z důvodu užívání obuvi pro jiný účel, než je určeno, nemůže být předmětem reklamace.     Pro pohodlí chůze vyberte správnou velikost a nejlépe vyhovující střihové provedení. Obuv si při nákupu pečlivě vyzkoušejte.     Obuv často střídejte, zejména v deštivém počasí. Obuv používejte způsobem a v prostředí odpovídajícím její účelovosti.    Při obouvání, zejména obuvi uzavřeného střihu, používejte obouvací lžíci a uzávěr (šněrovadla, spony, zipy) vždy dostatečně uvolněte, abyste zabránili prolámání nebo roztrhání patní části obuvi.     Každá přírodní useň je dobarvovaná a při zvýšeném pocení nebo provlhnutí obuvi může usňová obuv částečně pouštět barvu, individuálně podle agresivity potu!     Obuv chraňte před chemikáliemi, rozpouštědly a agresivními čistidly, které poškozují povrchovou úpravu svršku nebo podešev.     Usňová i textilní obuv s konfekčním šitím není vodotěsná. Promáčená obuv se nesmí sušit v kontaktu ani v bezprostřední blízkosti tepelných zdrojů! Mohlo by dojít k poškození obuvi a k deformaci svršku. Odolnost vůči promočení lze účinně zvýšit občasným používáním impregnačních přípravků proti vlhkosti.     Do uzavřené, zejména usňové obuvi po vyzutí napněte napínáky odpovídající velikosti a obuv nechejte vyvětrat a vyschnout.   \tNerovnoměrná kresba líce a částečná rozdílnost povrchu je charakteristická pro přírodní useň.    Kvalitní obuv není levná, proto ji denně pečlivě ošetřujte. Tím prodloužíte její životnost a bude Vám dobře sloužit.   Obuv za žádných okolností neperte v pračce! Došlo by k nevratnému poškození obuvi.      Návod na ošetřování jednotlivých druhů obuvi.                   Hladké usně - zbavit nečistot vhodným kartáčkem, měkkým  hadříkem případně vlhkou houbou. Suchou useň ošetřit krémem. Vyvarujte se rozmáčení, poškozuje vzhled povrchové úpravy a deformuje obuv. Pokud dojde k promáčení obuvi, dbejte na její včasné očištění, vysušení a nakrémování krémem určeným pro příslušný druh usně a typ její povrchové úpravy.                Vlasové usně - velury a nubuky - znečištění odstranit gumovým kartáčem, kartáčovat bez vydírání vlasu! Na ošetření jsou vhodné impregnační přípravky ve sprejích. Vlasová useň se nikdy nekrémuje.                Lakové usně - nečistoty odstranit měkkým textilem za sucha nebo za mokra. Po vysušení navlhčit olejem na obuv a potom vyleštit suchým flanelovým hadříkem. Povrch je choulostivý na chemické vlivy. rozmáčení a mráz.                Povrstvená useň - viz lakové usně. Při zanedbání předepsané péče může dojít k odlupování lícové vrstvy z usně!                 Plastové materiály - se snadno čistí vodou s přídavkem saponátu a po opláchnutí se vytře hadříkem. Vyhýbejte se náhlým změnám teploty.                Pryžové materiály - umýt a nechat volně obeschnout.                Textilní materiály - čistit kartáčováním, podle druhu textilu a povahy znečištění také vytíráním za vlhka, mastné skvrny čističem skvrn na textil.  Nebílit!            Toto značení informuje o materiálu, který tvoří nejméně 80% plochy dílců.                        - Vrch obuv                 - Podšívka a stélka                - Podešev           ","type":"short_text"}],"visibleBB":[[0,0,1920,1274],[0,0,1920,1274],[1884,75,1920,263],[471,0,1450,1274],[471,0,1450,1274],[481,0,1450,1032],[481,0,1440,124],[481,0,1440,83],[491,10,871,54],[493,12,849,56],[498,31,858,63],[498,12,858,56],[1129,5,1440,62],[1264,10,1390,30],[1264,10,1331,30],[1274,14,1330,26],[1331,10,1390,30],[1341,14,1389,26],[1144,30,1429,60],[1144,30,1389,59],[1391,30,1427,59],[871,5,1006,60],[876,10,944,27],[918,12,944,34],[876,34,1001,49],[876,49,1001,64],[932,49,977,64],[481,89,1440,124],[481,89,526,124],[481,89,526,124],[481,89,526,124],[491,94,516,119],[526,89,658,124],[526,89,658,124],[658,89,798,124],[658,89,798,124],[798,89,930,124],[798,89,930,124],[930,89,1077,124],[930,89,1077,124],[1077,89,1169,124],[1077,89,1169,124],[1184,89,1284,124],[1184,89,1283,124],[1361,89,1438,124],[1361,89,1437,124],[1329,124,1438,159],[1329,124,1437,159],[481,159,1441,952],[481,159,1440,191],[484,165,583,180],[605,165,652,180],[674,165,923,180],[483,196,1438,939],[483,196,1438,939],[483,198,1438,294],[485,198,937,745],[491,229,535,273],[535,229,579,273],[491,701,931,716],[491,273,931,713],[939,198,1436,294],[941,200,1434,292],[483,296,1438,518],[939,296,1170,518],[944,296,1164,508],[944,296,1164,508],[944,298,1164,315],[946,298,1071,315],[1073,298,1162,315],[944,317,1164,334],[946,317,1071,334],[1073,317,1162,334],[944,336,1164,353],[946,336,1071,353],[1073,336,1162,353],[944,355,1164,372],[946,355,1071,372],[1073,355,1162,372],[1073,355,1135,371],[944,374,1164,391],[946,374,1162,391],[944,393,1164,408],[946,393,1071,408],[1073,393,1162,408],[944,410,1164,425],[946,410,1071,425],[1073,410,1162,425],[944,427,1164,457],[946,427,1071,457],[1073,427,1162,457],[944,459,1164,489],[946,459,1071,489],[1073,459,1162,489],[944,491,1164,506],[946,491,1071,506],[1073,491,1162,506],[1172,296,1436,518],[1214,317,1394,497],[483,520,1438,666],[939,520,1170,666],[1172,520,1436,666],[1186,520,1436,666],[1188,522,1434,664],[1188,524,1434,574],[1190,524,1432,574],[1188,576,1434,662],[1190,576,1432,662],[1220,581,1397,611],[1220,614,1452,652],[1220,622,1401,645],[483,668,1438,743],[939,668,1436,743],[941,674,1031,694],[941,674,1031,694],[1031,674,1094,694],[941,709,1351,737],[941,709,1351,737],[941,709,1351,737],[939,745,1436,937],[942,749,1038,773],[957,754,1023,769],[1039,749,1135,773],[1061,754,1112,769],[1136,749,1232,773],[1143,754,1224,769],[1233,749,1329,773],[1248,754,1313,769],[1330,747,1426,773],[1345,752,1410,767],[942,773,1434,935],[973,779,1402,879],[948,889,1412,923],[973,933,1402,953],[948,958,1412,1048],[973,958,1402,988],[973,958,1094,973],[973,988,1402,1003],[973,988,1082,1003],[973,1003,1402,1018],[973,1003,1069,1018],[973,1018,1402,1033],[973,1018,1076,1033],[973,1033,1402,1048],[973,1033,1060,1048],[973,1048,1402,1076],[973,1047,1401,1076],[948,1081,1412,1456],[973,1081,1402,1111],[1209,1096,1342,1111],[973,1111,1402,1141],[973,1111,1110,1126],[973,1141,1402,1186],[973,1141,1389,1171],[1245,1156,1384,1171],[973,1186,1402,1231],[973,1186,1380,1216],[973,1201,1372,1231],[973,1231,1402,1261],[973,1261,1402,1336],[973,1336,1402,1366],[1213,1336,1254,1351],[1311,1336,1373,1351],[1146,1351,1356,1366],[973,1366,1402,1396],[973,1366,1345,1396],[973,1396,1402,1426],[1212,1396,1325,1411],[973,1426,1402,1456],[1137,1426,1261,1441],[973,1456,1402,1476],[948,1486,1412,1503],[973,1513,1402,1533],[948,1538,1412,2010],[948,1538,1412,2010],[948,1538,1412,1628],[948,1538,1008,1628],[948,1550,998,1616],[1008,1538,1412,1628],[1008,1538,1091,1553],[948,1628,1412,1694],[948,1628,1008,1694],[948,1628,998,1694],[1008,1628,1412,1694],[1008,1631,1097,1646],[948,1694,1412,1760],[948,1694,1008,1760],[948,1694,998,1760],[1008,1694,1412,1760],[1008,1697,1092,1712],[1008,1727,1405,1756],[948,1760,1412,1826],[948,1760,1008,1826],[948,1760,998,1826],[1008,1760,1412,1826],[1008,1778,1120,1793],[1008,1778,1409,1807],[948,1826,1412,1893],[948,1826,1008,1893],[948,1826,998,1893],[1008,1826,1412,1893],[1008,1837,1134,1852],[948,1893,1412,1960],[948,1893,1008,1960],[948,1893,998,1960],[1008,1893,1412,1960],[1008,1919,1130,1934],[948,1960,1412,2010],[948,1960,1008,2010],[948,1960,998,2010],[1008,1960,1412,2010],[1008,1962,1125,1977],[1101,1992,1151,2007],[973,2010,1402,2030],[948,2040,1412,2074],[973,2084,1402,2104],[948,2109,1348,2254],[948,2109,1348,2254],[948,2109,1348,2154],[948,2109,1064,2154],[948,2109,1048,2154],[1064,2109,1348,2154],[948,2154,1348,2199],[948,2154,1064,2199],[948,2154,1048,2199],[1064,2154,1348,2199],[948,2199,1348,2254],[948,2199,1064,2254],[948,2199,1048,2254],[1064,2199,1348,2254],[973,2254,1402,2274],[973,2279,1402,2299],[483,747,1438,937],[485,747,937,937],[485,747,564,828],[485,747,564,826],[481,939,781,952],[481,952,1440,1032],[484,965,1436,1028],[568,1008,668,1023],[588,970,668,1020],[668,1008,791,1023],[688,970,791,1020],[791,1008,946,1023],[811,970,946,1020],[946,1008,1043,1023],[966,970,1043,1020],[1043,1008,1243,1023],[1063,970,1243,1020],[1243,1008,1352,1023],[1263,970,1352,1020],[481,1032,1443,1274],[481,1034,1443,1204],[481,1044,1443,1183],[481,1046,1443,1181],[483,1046,603,1161],[483,1046,603,1064],[488,1066,628,1081],[488,1067,533,1081],[488,1081,628,1096],[488,1082,544,1096],[488,1096,628,1111],[488,1097,550,1111],[488,1111,628,1126],[488,1112,518,1126],[488,1126,628,1141],[488,1127,576,1141],[488,1141,628,1156],[488,1142,560,1156],[603,1046,1033,1146],[603,1046,1033,1064],[608,1066,748,1081],[608,1067,697,1081],[748,1066,888,1081],[748,1067,840,1081],[888,1066,1028,1081],[888,1067,977,1081],[608,1081,748,1096],[608,1082,713,1096],[748,1081,888,1096],[748,1082,803,1096],[888,1081,1028,1096],[888,1082,944,1096],[608,1096,748,1111],[608,1097,648,1111],[748,1096,888,1111],[748,1097,814,1111],[1033,1046,1193,1146],[1033,1046,1193,1064],[1038,1066,1178,1081],[1038,1067,1139,1081],[1038,1081,1178,1096],[1038,1082,1176,1096],[1038,1096,1178,1111],[1038,1097,1173,1111],[1038,1111,1178,1126],[1038,1112,1154,1126],[1038,1126,1178,1141],[1038,1127,1136,1141],[1038,1141,1178,1156],[1038,1142,1149,1156],[1193,1046,1293,1146],[1193,1046,1293,1064],[1198,1066,1338,1081],[1198,1067,1300,1081],[1198,1081,1338,1096],[1198,1082,1262,1096],[1198,1096,1338,1111],[1198,1097,1257,1111],[1198,1111,1338,1126],[1198,1112,1260,1126],[1198,1126,1338,1141],[1198,1127,1327,1141],[481,1204,1443,1240],[491,1209,901,1237],[491,1209,901,1237],[491,1209,901,1237],[481,1250,1458,1265],[1066,1250,1155,1265],[1228,1250,1433,1265]]}